AUTHORS
ChangeLog
LICENSE.txt
README.rst
requirements-test.txt
setup.cfg
setup.py
env_config/__init__.py
env_config/config.py
env_config/config_test.py
env_config.egg-info/PKG-INFO
env_config.egg-info/SOURCES.txt
env_config.egg-info/dependency_links.txt
env_config.egg-info/not-zip-safe
env_config.egg-info/pbr.json
env_config.egg-info/top_level.txt
env_config/snapshots/__init__.py
env_config/snapshots/snap_config_test.py
test/empty
test/env