Metadata-Version: 1.1
Name: env-config
Version: 1.9.0
Summary: Declare and load configuration from environment variables
Home-page: https://github.com/flowpl/env_config
Author: Florian Plattner
Author-email: me@florianplattner.de
License: MIT
Keywords: config
Platform: UNKNOWN
Classifier: Development Status :: 5 - Production/Stable
Classifier: Environment :: Other Environment
Classifier: Intended Audience :: Developers
Classifier: Intended Audience :: Information Technology
Classifier: License :: OSI Approved :: MIT License
Classifier: Operating System :: OS Independent
Classifier: Programming Language :: Python :: 3.5
Classifier: Programming Language :: Python :: 3.6
Classifier: Topic :: Software Development :: Libraries :: Python Modules
